imagewizard/__init__.py
imagewizard/version.py
imagewizard/helpers/__init__.py
imagewizard/helpers/helpers.py
imagewizard/image_analysis/__init__.py
imagewizard/image_analysis/api/__init__.py
imagewizard/image_analysis/api/analysis.py
imagewizard/image_analysis/api/colorspaces/__init__.py
imagewizard/image_analysis/api/colorspaces/color_analysis.py
imagewizard/image_analysis/api/colorspaces/dominant_colors.py
imagewizard/image_analysis/api/geometrics/__init__.py
imagewizard/image_analysis/api/geometrics/trim_to_content.py
imagewizard/image_hash_similarity/__init__.py
imagewizard/image_hash_similarity/api/__init__.py
imagewizard/image_hash_similarity/api/distance_algorithms.py
imagewizard/image_hash_similarity/api/similarity.py
imagewizard/image_hashing/__init__.py
imagewizard/image_hashing/api/__init__.py
imagewizard/image_hashing/api/hash_algorithms.py
imagewizard/image_hashing/api/hashing.py
imagewizard/image_processsing/__init__.py
imagewizard/image_processsing/api/__init__.py
imagewizard/image_processsing/api/processing.py
imagewizard/image_processsing/api/colorspaces/__init__.py
imagewizard/image_processsing/api/colorspaces/colorspaces.py
imagewizard/image_processsing/api/geometric_tfs/__init__.py
imagewizard/image_processsing/api/geometric_tfs/geometric_tfs.py
imagewizard/image_processsing/api/smoothing/__init__.py
imagewizard/image_processsing/api/smoothing/smoothing.py
imagewizard-1.1.2.dist-info/LICENSE
imagewizard-1.1.2.dist-info/METADATA
imagewizard-1.1.2.dist-info/WHEEL
imagewizard-1.1.2.dist-info/top_level.txt
imagewizard-1.1.2.dist-info/RECORD
