Metadata-Version: 2.1
Name: imagewizard
Version: 1.1.2
Summary: imagewizard is a python based library for performing various image manipulations and operations
Home-page: https://github.com/PriceSpider-NeuIntel/imagewizard
Author: Swaroop Padala
Author-email: soupspring47@gmail.com
License: MIT
Keywords: imagewizard,image hashing,hash,similarity,segmentation,image segmentation,image processing
Platform: UNKNOWN
Classifier: Development Status :: 2 - Pre-Alpha
Classifier: License :: OSI Approved :: MIT License
Classifier: Programming Language :: Python
Classifier: Programming Language :: Python :: 3
Classifier: Programming Language :: Python :: 3.4
Classifier: Programming Language :: Python :: 3.5
Classifier: Programming Language :: Python :: 3.6
Classifier: Programming Language :: Python :: 3.7
Requires-Dist: numpy
Requires-Dist: opencv-contrib-python
Requires-Dist: PyWavelets
Requires-Dist: pylint
Requires-Dist: scikit-learn
Requires-Dist: scipy
Requires-Dist: Pillow
